{
    "name": {
        "name": "Name",
        "visibility": true,
        "order": 1,
        "width": "20"
    },
    "lastHelped": {
        "name": "Last Helped",
        "visibility": true,
        "order": 2,
        "width": "15"
    },
    "affect": {
        "name": "Affect",
        "visibility": true,
        "order": 3,
        "width": "8"
    },
    "hand": {
        "name": "Hand",
        "visibility": true,
        "order": 4,
        "width": "8"
    },
    "lastActive": {
        "name": "Last Active Time",
        "visibility": true,
        "order": 5,
        "width": "12"
    },
    "loc2min": {
        "name": "Code in Last 2 minutes",
        "visibility": true,
        "order": 6,
        "width": "12"
    },
    "viewCode": {
        "name": "View Code",
        "visibility": true,
        "order": 7,
        "width": "12"
    },
    "submission": {
        "name": "Submission",
        "visibility": true,
        "order": 8,
        "width": "10"
    }
}